parse_opcodes/__init__.py
parse_opcodes/__main__.py
parse_opcodes-2.0.1.dist-info/METADATA
parse_opcodes-2.0.1.dist-info/WHEEL
parse_opcodes-2.0.1.dist-info/entry_points.txt
parse_opcodes-2.0.1.dist-info/top_level.txt
parse_opcodes-2.0.1.dist-info/RECORD
