Metadata-Version: 2.1
Name: parse-opcodes
Version: 2.0.1
Summary: takes a list of instruction names, opcodes, and arguments and turns it into a 32-column spreadsheet, with each column representing a bit
Home-page: https://github.com/coreydockser/parse-opcodes.git
Author: Corey Dockser
Author-email: coreydockser@gmail.com
License: BSD-3-Clause
Platform: UNKNOWN
Classifier: License :: OSI Approved :: BSD License
Classifier: Programming Language :: Python :: 3
Classifier: Programming Language :: Python :: 3.9
Requires-Dist: xlsxwriter
Requires-Dist: openpyxl
